{
	"@metadata": {
		"authors": [
			"Saederup92"
		]
	},
	"02f9cc543cd305f1": "Deaktiver bruger?",
	"0402fe5e15b200a7": "Administrer bruger",
	"0a0a90f6c5a99223": "Slet bruger",
	"153fb870fbe026b4": "Brugerkonti og profiler",
	"15cfe9cf42e4f59d": "Inviter brugere",
	"1a1707154be8a393": "Send invitationer",
	"1a708cefc9bb762c": "Bekræft godkendelse",
	"1ca5a286a8b17460": "Brugeren er endnu ikke blevet oprettet!",
	"1ca94ead58af110a": "Brugerens brugernavn.",
	"1cb4013146e4841e": "Musiker",
	"1e1f385cac7cacb9": "Allerede godkendt",
	"226329607d4cf3b1": "Kontoaktivitet",
	"229981dd1dc44fcc": "Forhold",
	"2540837f31fad968": "Brugeren er allerede blevet oprettet!",
	"2809977bb7b3c01b": "Ikke en administrator",
	"2b7ce51022626c2b": "Vis kun botter",
	"310e712e2fe9dba0": "Deaktiver eller aktiver denne bruger.",
	"334904d98dfdb21f": "Tilmeldte sig før",
	"35febdaad02a5328": "God bedring,\nPhabricator",
	"36c00d465ed8b480": "Bekræft invitationer",
	"38db411381200782": "Ingen kontoer fundet.",
	"3a3192e2791c5786": "Bot",
	"3a7eab135187ac47": "Opret ny bot",
	"3d1ae03a1205e415": "Nyt brugernavn er påkrævet.",
	"3f1c9b2149f85753": "Fjern som administrator?",
	"41b81eb8db1b97e8": "Godkendt",
	"46667b46465565cf": "Ikke en almindelig bruger",
	"47dcc27d6e87ece8": "Roller",
	"480c511a4dbc9b01": "Skjul brugere med MFA",
	"4a153b60a946eba6": "Brugerbillede",
	"4b37cfc453fcd6bb": "Brugernavne",
	"4b9bde480b250ad3": "Opret ny bruger",
	"4ca88ea465a93d07": "Botter",
	"4ca8d2249d598179": "Du har ikke tilladelse til at oprette brugere.",
	"4d47d0b032207d66": "Brugerprofiler",
	"4e506cc0e4cdde5a": "Postlister",
	"4e7afebcfbae000b": "Administrator",
	"54fac9ae8e6152f6": "  $1",
	"55e395d7bbd76d57": "Omdøb bruger",
	"56dc31961dd1059f": "Skjul botter",
	"5addd7d6b4f9f393": "Brugerdetaljer",
	"5b7dcd14a4faa2cd": "brugere",
	"5e838fce10907ec5": "Godkend bruger",
	"6345b3a4fde47ce6": "$1 deaktiverede denne bruger.",
	"64314c70d7a0770a": "Deaktiver bruger",
	"674866c78d05d6ad": "Billede fra $1",
	"681b5b5ae10b994e": "Tilgængelighed",
	"69189a95ef784fb8": "administratorer",
	"6b61da0fdc10df15": "Aktiver bruger",
	"6f9b9af3cd6e8b8a": "besked",
	"7389b3b752fac40a": "Dyr",
	"76fe9e6ab29a48b6": "Nyt brugernavn: $1",
	"77dda76690d4a8c2": "Skjul deaktiverede brugere",
	"7a2c34cb789c0fca": "Logistik",
	"7b2c7f146abacedd": "Godkend",
	"7c7e1b6b346cd9e7": "Læs information om brugere.",
	"7fce7367708c3e3c": "Skjul ikke-godkendte brugere",
	"82ba679ec45ed97e": "Handlingsnavn",
	"85d1e1a855e2ef70": "Ikke godkendt",
	"884291304cc41383": "Rediger bruger: $1",
	"8c03d236ca3dc6e4": "$1 omdøbte denne bruger fra $2 til $3.",
	"8cb6ad8731e7a053": "Godkend brugeren.",
	"8f3c08133aacb6ef": "Rediger profilbillede",
	"8fe432e681964c5e": "Har MFA",
	"906bd1cb190869c5": "Projekter ($1)",
	"909bf3e80731a458": "Gem profil",
	"92d0e65449810eaa": "Brugerkonti",
	"9466f509685e3f2b": "Vis kun deaktiverede brugere",
	"973ed06fc58a3167": "Rediger profil: $1",
	"9778204166e095f3": "Gør til administrator",
	"9b67737669fd99f2": "Tilmeldte sig efter",
	"9e3100639feb4d6b": "Fjern administrator",
	"a1924aaadbcff174": "Gør til administrator?",
	"a3c29f80a5be67a7": "Skjul administratorer",
	"a6935da6add92db1": "Indtast et brugernavn...",
	"a901bea47bfb2da4": "Gammelt brugernavn: $1",
	"a9414b4e4c1232c2": "Rediger indstillinger",
	"aed3b8c6a7c0fbbd": "Verificeret",
	"b25c91fe6103401c": "Opret bruger",
	"b2cdd74280dbd709": "Ikke-godkendt konto",
	"b34e9360db16298e": "Ændre brugernavn",
	"b37554f695b15005": "Personer",
	"b5c499421051e6e7": "Deaktiver brugeren.",
	"b88d5070610713c2": "Godkend eller afvis brugeren.",
	"b8fc1450c62d174c": "Gammelt brugernavn",
	"b97cccf3af4a9a50": "Brugernavnet er ugyldigt! $1",
	"bc1e5b3b5e523108": "Bruger tilgængelighed",
	"bdeb88d61b7bf453": "Kan deaktivere brugere",
	"c1faabc1d40aaf24": "$1 afviste denne bruger.",
	"c33ff01f3b013690": "Du skal være en administrator for at godkende brugere.",
	"c4b5e97b440a70e0": "Liste over kontoroller.",
	"c4c061d266032ace": "Postliste",
	"c7ef2edb54168e52": "Kun du kan redigere dine oplysninger.",
	"cd280a41f75884f7": "Rediger profil",
	"cf614f7522cb8544": "Vis kun postlister",
	"d0652d5a3d5daf73": "Gennemse ejere",
	"d3e8e92a94f192f4": "Bruger er deaktiveret",
	"d7f47bd5af71bd47": "Hej $1",
	"db18bd8b31f5d6c8": "Log af $1",
	"dc16f2b254daf60e": "Brugernavn: $1",
	"e43d612e11f1568f": "Log af",
	"e598bbf2dda9d06e": "Godkend konto",
	"e8e5d593fcb0dc6f": "Aktiver bruger?",
	"ea424d38af72dd13": "IP",
	"ebe941cc14c0aebc": "Mangler godkendelse",
	"ed2610e9d1945355": "Invitationer",
	"ed7e09ad1efa8821": "Vis kun administratorer",
	"f0ed165f0673a337": "Ikke-godkendt(e)",
	"f3afff1f70d65daa": "Nyt brugernavn",
	"f43af23677593e4c": "Bruger-PHID",
	"f98db0153727189a": "Bruger siden",
	"f9a76abef3d379b9": "$1 aktiverede denne bruger.",
	"ff69626f5c7ab4d3": "Kontotype"
}
