{
	"@metadata": {
		"authors": [
			"Liuxinyu970226",
			"NikosLikomitros",
			"Nikosgranturismogt"
		]
	},
	"01ad122ef5d1a3df": "Ένας διαχειριστής έθεσε το Phabricator σε λειτουργία μόνο για ανάγνωση.",
	"0cc06ea98df1b9dd": "Πανικός!",
	"11a8e6be14c3dffe": "Χωρίς γράψιμη βάση δεδομένων",
	"1cb5f5cf31a0ab68": "Καταστροφή του $1 **$2***...",
	"23a7b8321b13ebd3": "Το αντικείμενο \"$1\" δεν μπορεί να καταστραφεί (δεν χρησιμοποιεί το $2).",
	"24d1d3058b56700b": "Χωρίς υποστήριξη κωδικοποίηση",
	"2a3d3ded34ffe3e9": "Δεν υπάρχει τέτοιο αντικείμενο \"$1\"!",
	"2f81b1b51a0ff80f": "Μηχανή: Καταστροφή",
	"35f8b97d2a70bb5c": "Καταστροφή αντικειμένων μόνιμα.",
	"3e3549849220a546": "$1 ανά ώρα",
	"422c87b46689da19": "Βαθμολόγηση Περιοριστικών Ενεργειών",
	"464c7e7834d9d7bd": "Σύνταξης",
	"46ef097ca8f49509": "Αποτυχία φτάσιμου στον μάστερ",
	"4f17eb3453bbf2ad": "$1 αντικείμενο(-α) καταστράφηκαν μόνιμα.",
	"52aa5f90323d30f5": "Επιλογή κωδικοποίησης",
	"58bf20abc8cfcd7f": "Σημαντικό",
	"65fca1e4d02e4304": "Μητρώα καταστροφής",
	"663a7169eba04995": "Αυτό μάλλον σημαίνει μια πολύ λανθασμένη διαμόρφωση ή σημαντική διακοπή της υπηρεσίας.",
	"6a1114f49dc5b54a": "Η καταστροφή αντικειμένων είναι σε εξέλιξη...",
	"6bebb0e6346bd254": "Αυτό το σύστημα είναι ενεργό γιατί δεν υπάρχει σημαντική βάσξ δεδομένων ''$1'' στην επιλογή διαμόρφωσης ''$2''.",
	"8140de1e81df20b1": "Επιλογή κωδικοποίησης χαρακτήρων",
	"89fe6d3157dc3d41": "Τα δεδομένα θα καταστραφούν για πάντα",
	"90ce40dfd99492ff": "Επιλογή Σύνταξης",
	"b5b85dd7e24d2532": "Ως διαχειριστής, μπορείτε να αναθεωρείτε πληροφορίες καταστάσεων από το πίνακα ελέγχου $1. Αυτό ίσως παράσχει περισσότερες πληροφορίες για την τρέχουσα κατάσταση των πραγμάτων.",
	"bc0792d8dc81e8aa": "Σύστημα",
	"e4fdfba6be0afcb4": "$1 ανά λεπτό",
	"e6e08d9d69b29e13": "Η μέγιστη επιτρεπόμενη τιμή για αυτήν την ενέργεια είναι $1. Προωθείτε ενέργειες στην τιμή $2.",
	"e9cca27a6fbae913": "Διαχειριστική λειτουργία μόνο για ανάγνωση",
	"eb8d81d4d4ee2b99": "$1 ανά δευτερόλεπτο",
	"f0cd9813b64afd83": "Ορίστε ένα ή περισσότερα αντικείμενα για καταστροφή."
}
