{
	"@metadata": {
		"authors": [
			"Kly"
		]
	},
	"0154c0dabe7145db": "在此",
	"02a839a53904db72": "有人在文章上做了評論。",
	"02aa91aa30803982": "下一篇文章",
	"0322aeea73679cc7": "撰寫文章",
	"037c6223f05d36c4": "管理部落格",
	"04b4ef32c8d15ec3": "部落格名稱。",
	"05cba97abf2762b8": "此文章已被封存，這僅會被您已級能編輯$1的其他使用者看見。",
	"09784e9c87e2503d": "閱讀關於部落格的資訊。",
	"0ac1c08888a52d41": "在 Phame 建立或編輯部落格。",
	"0b40066ab2af8fed": "封存的文章",
	"0b9d2b2362bc3358": "部落格",
	"0d05e8bbeb83b625": "文章必須附在部落格上。",
	"121e1619b93435d2": "部落格描述。",
	"1692853416a67e54": "生效部落格",
	"18c02e337aea37ac": "$1 標記了$2為封存。",
	"19e03f67f213f4a5": "部落格 PHID。",
	"1c43492094e14968": "編輯部落格圖片",
	"1c56846eb6051be9": "以一些部落格來搜尋文章。",
	"1c5e25896115c292": "文章副標題。",
	"1d0783057d410ef4": "沒有外部網域",
	"1e853b892c3eb28e": "此部落將會再次生效。",
	"1e95ea2970c6510c": "最近文章",
	"1ea38735b6d23837": "內部與外部部落格",
	"1ea68b69b9ace3c4": "更改文章正文。",
	"21c3bbaf4a3ad2af": "Phame",
	"2430d540db72f93f": "您沒有權限建立新的部落格。",
	"251c6849257f67ae": "刪除標頭",
	"2581b628cba259f5": "閱讀關於部落格的文章。",
	"2621c6fd51a58e1d": "封存",
	"28bfc726013fcbfc": "$1 更新了文章內容。",
	"2a84dcc01a566ae6": "封存的部落格",
	"2a85d80f9741af4a": "移動文章",
	"2d9719303474b3b9": "更新新的標頭",
	"2dbc63588a905b8a": "找不到部落格文章。",
	"30060691b25bae4c": "所有部落格",
	"30169101a26b1427": "文章正文。",
	"305660be297abb22": "部落格的訂閱者更改。",
	"31341c6f0c7af677": "標頭",
	"31962e3c4d0ca1a5": "文章作者的 PHID。",
	"33a5e22a2c753784": "$1 標記了$2為草稿。",
	"3454c4ae2ae66c39": "這裡沒有任何可見的部落格文章。",
	"34c153562b5f23b7": "新文章標題。",
	"3685b61dac16f010": "[沒有部落格]",
	"3a56871e5a6c55b3": "設置部落格文章形式",
	"3b80d206d2f953b8": "此部落格將會被標記為封存。",
	"3e36cde128f96ca8": "您沒有草稿文章。",
	"3ea51b57f6b8a1e3": "父級站台名稱",
	"3eb800a9594bbf57": "新的部落格狀態常量。",
	"3f11c6eac93522cf": "更改部落格副標題。",
	"46231616f5742eea": "副標題不可超過 $1 個字元。",
	"46a491b335ecec76": "新部落格標題。",
	"474461ddfad9338c": "草稿文章",
	"47868c588b8ac45a": "編輯標頭圖片",
	"4b8740062e5dde7f": "部落格完整網域 URI。",
	"4cb32aba43c98908": "$1 建立了此部落格。",
	"4cf7f535a407c982": "重新更改部落格標題。",
	"4d91986fd792a447": "部落格標頭",
	"4dcc0a9ac146f4f5": "由 $1 在 $2 撰寫。",
	"50d4776cd97c5663": "部落格必須要有名稱。",
	"52c9e35eb2b1081c": "編輯部落格標頭",
	"52d8128c6444ca70": "草稿文章",
	"53231bc6156bc0d5": "文章標題。",
	"5326c7d856f69190": "若您封存了此文章，這僅會被能編輯$1的使用者看見。",
	"53a4cd58d0b84466": "更改到部落格描述",
	"55cab7d5b597d22d": "Phame 部落格",
	"562c21e0369d2ab4": "$1將此部落格從$2改名成$3。",
	"5736432cce18baf8": "文章的內容更改。",
	"57de6ae9d76591d4": "更改部落格父級網域名稱。",
	"5808e31a51ff59da": "建立部落格",
	"58a928452850f1fd": "文章移動成功。",
	"58c3d4052b3bd807": "新文章正文。",
	"5a1f694ac79982c2": "生效部落格",
	"5aee5d9254f38d5b": "本地部落格",
	"5b65037351caeb0e": "404 找不到頁面",
	"5ef4439786692eab": "部落格",
	"6058e81612cb4e76": "更改部落格父級站台名稱。",
	"6080af4be473d06f": "更改文章可見性。",
	"650f11beb25aa00c": "上一篇文章",
	"6934ceeb38844e69": "沒有描述。",
	"6b81e33d939a7bf5": "新部落格父級站台名稱。",
	"6bdcc083a864c2fb": "Phame 部落格",
	"6c131ec6f645ef0e": "$1 建立了篇文章。",
	"6c8d4a5b4205da64": "部落格文章",
	"6cc2427c8da2d17b": "編輯部落格",
	"6e643a4c7cf547b9": "新的部落格完整網域 URI。",
	"6faf551334fc913a": "$1 更新$2的副標題。",
	"700d6f4b11efda16": "管理部落格",
	"707e8f4dbad5677b": "完整網域 URI",
	"70eb82182e507d4f": "編輯文章標頭",
	"718a7e8a582e982e": "正文",
	"720ea877ad353170": "無父級站台",
	"751fd5e6c9bfbc54": "新文章副標題。",
	"756ae1a627913e86": "建立新的文章",
	"768802e2171cbd59": "找不到部落格。",
	"7852e583b7b01164": "父級站台",
	"7858ac3ff63354f3": "文章",
	"7cf1129813b2c7e5": "$1 封存了此部落格",
	"7d99fb9e1f1f739d": "$1 封存了此文章。",
	"7d9ff4f0de398581": "可見性",
	"7e6b2e8b8f224285": "文章詳情",
	"81c6ca3121489518": "部落格的詳情更改。",
	"81db9daae384589c": "部落格副標題。",
	"86503414c8d8c3b6": "由 $1 封存文章。",
	"86eb6eb29c614413": "無父級網域",
	"893c0db60fd595ef": "Phame 文章",
	"8b6bf007284e7caf": "部落格父級網域名稱。",
	"8b9a9e106e69e42f": "$1 封存了部落格 $2。",
	"8d09e8be0406c579": "在 Phame 建立或編輯部落格文章。",
	"8e207a5566f64494": "建立部落格",
	"8fb175b3010efcc8": "文章標題。",
	"952be7af2fb5404b": "Phame 文章",
	"9a088442be12a2c9": "部落格文章",
	"9cd802f405ac83e3": "更改部落格描述。",
	"a0197edbdf496f4a": "更改文章副標題。",
	"a14ddebdef0e7a08": "父級站台 URI",
	"a223a076881cfd2a": "撰寫文章",
	"a4a31ebdce7b463e": "落格父級站台名稱。",
	"a5872f6eb8ee6856": "Phame 使用者指南",
	"a8fb1ea76e7c87f8": "部落格詳情",
	"b953e2ea2914ce83": "文章可見性。",
	"baabbb178f3b29fb": "文章標頭",
	"bb80f0f68e813aef": "生效或封存部落格。",
	"c0505809abddd71d": "建立新的部落格",
	"c06d93054afc3ca1": "新部落格描述。",
	"c13a9e029cdd6c56": "文章正文。",
	"c2f42c6ad3d6747d": "關於$1",
	"c439b61c1714100c": "封存部落格",
	"c480c19e211cc183": "部落格：$1",
	"c48de9b34f2627e0": "封存文章",
	"c523b7bd917b6fdd": "重新更改文章標題。",
	"c60c4661972204fe": "部落格圖片",
	"c6187d71b030639c": "部落格名稱。",
	"c6c69df98af47065": "設置 Phame 部落格形式",
	"c8e29cc051372b92": "搜尋文章",
	"d6a46ca785a9f04c": "新部落格父級網域。",
	"d78b9d3283b39499": "上傳標頭",
	"e159d05a124cfbe6": "副標題",
	"e1d839835205c3c1": "即時查看",
	"e39db4e813824823": "不在部落格",
	"e4616d2b43d52500": "瀏覽部落格",
	"e5157b9df1023a45": "編輯文章",
	"e62d3c2b6a6d43a9": "完整網域",
	"e68c968d841e4965": "部落格文章：",
	"e82425edd238d93e": "輸入部落格名稱…",
	"e82dc3ff74bdb71a": "文章必須要有標題。",
	"f0e501b1be38ce3c": "所有文章",
	"f359318e1fd31d43": "父級網域",
	"f41b51451b0edef8": "建立部落格",
	"f597b0365907aa0f": "可建立部落格",
	"f63020b52bd06509": "新部落格副標題。",
	"f90b7c973bea4355": "更改部落格的完整網域 URI。",
	"f9bda05e0989b87f": "封存的文章",
	"f9c83d446816b967": "Atom URI",
	"fbe1d55114733988": "（空文章）",
	"fc0cb20e7507b1e1": "此部落格沒有可見的文章。",
	"ff33d391c891a98b": "文章歷史"
}
