{
	"@metadata": {
		"authors": [
			"Wladek92",
			"Zarisi"
		]
	},
	"0035403387839cb4": "Aucun résultat.",
	"01b86a4d55b3406f": "Cet élévénement de menu est très important et ne peut être désactivé.",
	"037162cdf0ff4298": "Eléments du menu personnel",
	"05b09bdf064bf97d": "Le format d'exportation n'est pas disponible",
	"06cc85b4876371df": "Moteurs de recherche",
	"103e474eb68c3eb2": "Désactiver un élément de menu",
	"10cb8570b888d286": "Echec lors du chargement du PHID utilisateur « $1 » !",
	"1315cf907892b7bf": "Il n'y a pas encore de requête active.",
	"1cce890485500d1a": "Ignorer les noms communs",
	"21252eb657cf9de2": "Eléments globaux de menu",
	"238d9a5d440324de": "Vous devez choisir un nom d'étiquette.",
	"23da0b3f82b6d619": "Modifier le menu de votre compte peronnel.",
	"26309769e1bae46e": "Spécifier soit --reset soit --threshold.",
	"270aa2928cc52994": "Aucun service n'a besoin d'être initialisé.",
	"295d39d4c2776cc4": "Ajouter un nouvel élément de menu ...",
	"2ecaff5bb50574d1": "Modification d'élément de menu : $1",
	"38d663fb82d05656": "Trouver les objets correspondant à une requête de recherche sur texte complet. Pour davantage de détails, voir le « manuel utilisateur de Search » dans la documentation.",
	"3bbfc441e6d0de04": "Activer un élément de menu",
	"3ee8dd9cfcc9ff3d": "Les éléments du menu profil ne peuvent pas être générés sans un contexte d'objet.",
	"400067c1c8b38d3c": "$1 objet(s) de type $2 en cours d'indexation.",
	"405f3d6bca1c0da7": "Menu de configuration",
	"41db655cec1cfb89": "Rechercher les erreurs",
	"42c477190a22db63": "Action « $1 » non prise en compte sur l'élément.",
	"4329a7c2771cca43": "Non supporté.",
	"45d7c39dc032801d": "Vous ne pouvez pas créer cette relation car elle ferait apparaître des dépendances circulaires.",
	"481e63e8ab09e8c3": "La classe du moteur est nulle.",
	"484fad982283bb18": "Élément obligatoire",
	"4b1146a0727f1a1d": "Eléments du menu profil",
	"4c17ecfe7def5613": "Initialiser ou réparer un service de recherche.",
	"516b29d349442301": "Champs d'objet",
	"5522729536fd8eb3": "Elements du menu",
	"57e13e92fda0d691": "Requête cachée",
	"5bb93ae23434827a": "Constantes prises en charge par la contrainte `$1` :",
	"5dd6cbe36cb8278d": "Désactiver cet élément de menu ? Il n'apparaîtra plus dans le menu mais vous pourrez le réactiver plus tard.",
	"5de8bfb3dbacf28b": "(voir le tableau ci-dessous).",
	"5e9364f7f349107f": "Définir comme élément par défaut pour ce menu ? Les utilisateurs qui arrivent sur cette page verront par défaut, le contenu de cet article.",
	"62c228214722b70b": "Eléments du menu actuel",
	"6544533c5e4cd736": "Elément de menu",
	"6c05e4665abdcf38": "La requête (avec l'ID « $1 ») a déjà été enregistrée. Les requêtes sont immuables une fois enregistrées.",
	"6dfeeefcb45cdbd2": "Etat du document",
	"729d27dbefe518d0": "\"2022-12-25\" ou \"il y a 7 jours\"...",
	"736b4fec7a510e4d": "Pagination et limites",
	"7661a07ddf968876": "Ce moteur est utilisé pour modifier les éléments de menu sur les profils.",
	"776ccdd708fc908c": "Supprimer un élément du menu",
	"785d2ecf4f7686ee": "Les chats passent la plupart de leur temps à comploter pour tuer leur propriétaire.",
	"7d623da1772a39f8": "Créer un élément de menu",
	"90b65eed1b0db481": "Désactiver la consultation",
	"912fc14508efbb60": "Diviseur",
	"91ea608dd6e15158": "Menu de gestion",
	"94005b0756b4c7dc": "Le plus grand chat enregistré avait 11 onces de longeur, à partir du nez jusqu'à la queue.",
	"990e155d2d17a6f3": "Le moteur de recherche (« $1 ») définit un champ d'exportation avec une clé (« $2 ») en conflit avec un autre champ. Chaque champ doit avoir une clé unique.",
	"99dfb651a7f5bb64": "PHIDs",
	"9ae7f6ea0457f978": "Sauvegarder la requête",
	"a0e142ac9dc3396e": "Alias obsolète pour « $1 ».",
	"a345d338fc9e8de7": "Modifier un élément de menu",
	"ab5406b8508263b8": "« $1 » doit être une date antérieure à « $2 ».",
	"b29f8014721a1064": "Actuellement, ce menu n'a pas d'éléments.",
	"b3c8a1c8fb291e4e": "Types de document",
	"b3d8c0b0eb9cf873": "Cet élément est déja défini comme élément par défaut pour ce menu.",
	"b42827a53fc1aea6": "Manuel utilisateur du menu du profil",
	"b810678b178d4d4e": "Choisissez un format d'exportation valide.",
	"bab1403abf1d6010": "Le moteur de recherche (« $1 ») a exporté un mauvais nombre d'objets, attendu $2 mais obtenu $3.",
	"bce06414177f72ab": "Chercher",
	"bdb5ec5bba911ceb": "Supprimer cet élément de menu ?",
	"bf92416c53d30c42": "Les chats préfèrent la glace à la vanille.",
	"c237ff35cf32eab1": "Exporter les résultats",
	"cebf22aba7c50b6f": "L'extension du moteur d'exportation (« $1 ») a exporté un mauvais nombre d'objets, attendu $2 mais obtenu $3.",
	"d0517071aa376e79": "Lien",
	"d2048ad922d4acee": "Cet élément ne peut pas être défini comme élément par défaut. Cela est généralement dû au fait que l'élément ne possède pas de page, ou possède un lien vers une page externe.",
	"d5f768f644a880a6": "Recherche exacte",
	"d63e36e0856ed938": "Activer cet élément de menu ? Il réapparaîtra de nouveau dans le menu.",
	"d9cda2eb48275f7c": "Désactiver la consultation ?",
	"e2910edc37b6b756": "Vous ne pouvez pas créer un lien vers l'objet  « $1 », car l'objet n'existe pas ou n'a pas pu être chargé.",
	"e4580c9a4ca3a13d": "$1 (non disponible)",
	"ecd57be6ef1b7a16": "Le décalage pour la requête est trop grand. décalage+limite=$1 (maximum=$2)",
	"f24dd6bce4f0f1ab": "L'extension du moteur d'exportation (« $1 ») définit un champs d'exportation avec une clé (« $2 ») qui provoque un conflit avec un autre champ. Chaque champ doit avoir une clé unique.",
	"f601e90879bdb418": "Exporter les données",
	"f740ffa51038d0a1": "Dépendance circulaire",
	"fb3ead7540c714d9": "Le seuil doit être supérieur à 0,0 et inférieur à 1,0 .",
	"fde9b5b16a32243f": "Fonction de recherche « $1 » inconnue. Les fonctions supportées sont : « $2 »"
}
