{
	"@metadata": {
		"authors": [
			"Ykhwong"
		]
	},
	"045bc6c93af84113": "해당 문서가 없습니다.",
	"0691c225d7708594": "더 오래된 판 $1 편집...",
	"098849bb44e7532c": "문서 차이",
	"0bcbc5e9740f8ee2": "이동한 문서는 다시 이동할 수 없습니다.",
	"0c3091edafbec0d1": "다음 변경사항 »",
	"0cb0697324e584a3": "초안 게시",
	"0fc28db091e83c15": "이동됨",
	"1e57779e9843e6d4": "문서 내용",
	"24753df10adddc21": "알 수 없는 문서 상태 '$1'!",
	"26f7b3ad79583865": "문서를 삭제할 수 없습니다!",
	"27823bb42bb74e84": "알 수 없는 URI 유형 '$1'!",
	"2d40c7f9ffeda6d6": "여기에 문서가 없지만 만들 수 있습니다.",
	"3c25ce154a917b9c": "더 보기...",
	"42324a059b503ec2": "저장하고 게시",
	"470633416556b7fc": "현재 경로",
	"49bc79f402e8e620": "(제목 없는 문서)",
	"4eb2c082653c8e10": "$1님이 이 문서를 $2(으)로 이동했습니다.",
	"4f9be057f0ea5d2b": "내용",
	"525ffd3e4b74abba": "이 문서의 게시된 판을 과거의 판으로 되돌리시겠습니까?",
	"546d5cdcb6a3f042": "판 $1",
	"5d303d091f912156": "현재 판 $1 편집...",
	"5e7169b52a97cd95": "이 문서 편집하기",
	"5e971cacb60f7fdc": "문서 역사: $1",
	"69068fa8718451b6": "위키 문서",
	"6abcea27f878afc8": "초안판 $1 편집...",
	"6cf6e0d91a8abee7": "이 문서의 게시되지 않은 초안을 보고 있습니다.",
	"6d65ea1ca0a74675": "$1님이 이 문서를 삭제했습니다.",
	"7fb270d05669a23f": "$1님이 $2의 새로운 판을 게시했습니다.",
	"80414c97b50c6eaa": "해당 문서가 존재하지 않습니다.",
	"83712b6a75530065": "$1 문서는 이미 존재합니다. 대신 편집하시겠습니까?",
	"872a978d3c0f77c5": "문서 내용의 변경사항",
	"8828d46deef6929e": "$1님이 $2에서 $3(으)로 이동했습니다",
	"8906f3e5c78fa3b9": "초안을 게시하겠습니까?",
	"891f3732e475a137": "문서가 삭제되어 있습니다.",
	"8c5835ec7be7977b": "$1 경로를 대신 사용하시겠습니까?",
	"8fe82457801b6ad1": "문서를 삭제하시겠습니까?",
	"94dd7716959724e1": "문서에 내용이 있어야 합니다.",
	"96a9105f070e8b82": "\"$1\" <$2>",
	"9837ef4032a3aed8": "문서 역사",
	"98b219af6d77a4ff": "초안 $1",
	"9c062d190c7fb27c": "문서가 이미 존재합니다!",
	"9cfac843308844f9": "$1님이 $2을(를) $3(으)로 이동했습니다.",
	"a2ed8b5157f5716b": "« 이전 변경사항",
	"ab240038516f0c16": "초안 보기",
	"ab703808f582e5fd": "편집 충돌",
	"ac4ccb43b8c170bf": "이 문서는 게시되지 않은 초안 변경사항을 포함합니다.",
	"af3f32e27eb9fddf": "$1님이 이 문서의 새로운 판을 게시했습니다.",
	"b63cdeb4d5e38fd3": "이 문서의 게시된 판을 더 새로운 판으로 업데이트하시겠습니까?",
	"b6657899cdf6cabb": "$1님이 제목을 $2에서 $3(으)로 변경했습니다.",
	"b725bf3f57421947": "더 오래된 판을 게시하시겠습니까?",
	"c031325de7d7d3a7": "초안으로 저장",
	"c24761b6c8f4f4f2": "편집자: $1",
	"c39125e9c12cb9ae": "여기에 문서가 없습니다",
	"d41b84d90b5e3658": "더 오래된 판 게시",
	"d791d0dcd4f05e31": "이 문서 만들기",
	"d7ad6e9bb987056f": "Phriction 문서의 편집을 위해 이 엔진이 사용됩니다.",
	"d9ff972ab89343fe": "편집",
	"da494e8452bfdde4": "이미 게시됨",
	"e379350364d75f1f": "모든 내용",
	"e637d9faea1e24d9": "페이지를 찾을 수 없습니다",
	"e69f5da60a4e048b": "새 문서",
	"e934de8564da9b0e": "빈 문서",
	"ea23c7d5b2b63717": "여기로 이동"
}
