{
	"@metadata": {
		"authors": [
			"Derugon",
			"Thibaut120094",
			"Verdy p",
			"Wladek92",
			"Zarisi"
		]
	},
	"0006324868d87fff": "Description longue de l’initiative.",
	"09da16816c90724b": "Risques et défis de l’initiative.",
	"0c65384c668ba13b": "$1 a fermé cette initiative.",
	"0df1e70d42585378": "Trouver des soutiens",
	"131126db1d0ec867": "$1 a créé cette initiative.",
	"13c34960119d427a": "Créer une initiative",
	"1b6864bd678747f7": "Les initiatives doivent avoir un nom.",
	"1b7b622199d21863": "$1 a mis à jour les risques/défis de l’initiative $2.",
	"1bb2fbea87f0ff29": "Fermer l’initiative",
	"23a23ea6bf8ef315": "Une autre activité d’initiative non listée ci-dessus s’est produite.",
	"267ef5e7c9936128": "Toutes les initiatives",
	"26ac3f1c80c96ce1": "Vous ne pouvez pas soutenir une initiative fermée.",
	"2b43bd1cd7561a21": "Modifier l’initiative : $1",
	"2f2c6f8ae8a896fc": "Nouveau marchand de l’initiative.",
	"2ff63d49f3db15b5": "Rouvrir l’initiative",
	"31332d46fa9c350b": "Payable au marchand",
	"34f0b08914211401": "Nom de l’initiative.",
	"3d8a9ebcfdb24479": "Financer les initiatives",
	"419984bf9d760209": "Financer l’initiative",
	"496f16806cb7768e": "Nom de la nouvelle initiative.",
	"4dfaedd3349df90d": "MODIFICATIONS DE LA DESCRIPTION DE L’INITIATIVE",
	"50ff6afbf676fbbc": "$1 a mis à jour la description de l’initiative pour $2.",
	"520efa3d86e2177b": "$1 a soutenu cette initiative avec $2.",
	"52871104046f69e8": "Initiative",
	"5535359ccb6b8ccf": "Aucune initiative trouvée.",
	"5554ce77716f9f86": "Financer des soutiens",
	"57b239df5d5959e7": "Financer un soutien",
	"595ee8bb5ee7b517": "$1 a créé l’initiative $2.",
	"5d6f6c0bec25a127": "Financer <initiative inconnue>",
	"5f8780d0cc6166f2": "Financer",
	"633ad62e2952a2b6": "Voulez-vous réellement rouvrir cette initiative ?",
	"6706a71634f7f1da": "Description de la nouvelle initiative.",
	"68c17ef366561d64": "Initiatives détenues",
	"68c599ba73d209b4": "Soutenir $1 $2.",
	"6990c9f9ede719be": "$1 a de nouveau financé $2 à $3 pour $4.",
	"6fd1df7dfa78cabb": "Soutiens",
	"705770f5049f7cf4": "Vous n’avez pas le droit de créer des initiatives de financement.",
	"71ceafe77177743b": "$1 a défini le marchand recevant les financements de cette initiative à $2.",
	"7257e40f24c977b6": "Impossible de charger $1 !",
	"74ce2254c0749295": "$1 a soutenu $2 avec $3.",
	"76060d1ed132cdf8": "Vous devez spécifier combien d’argent vous voulez contribuer à l’initiative.",
	"7941a8fba64f4b0e": "MODIFICATIONS DES RISQUES / DÉFIS DE L’INITIATIVE",
	"7c0144ad383829b9": "Vous devez spécifier un compte.",
	"7c5e1a1c6502adba": "Créer une nouvelle initiative",
	"822d44def2c2200a": "Ouvrir les initiatives",
	"82a5e745c1d94a8e": "$1 a mis à jour la description de l’initiative.",
	"8464422f887a320f": "Politique d'affichage par défaut pour les initiatives créées récemment.",
	"84b171722830d75f": "$1 a changé le marchand recevant les fonds pour $2 de $3 en $4.",
	"8998e1389dfe9094": "Aucun soutien trouvé.",
	"8bb95f22bf97e9c8": "Risques / défis",
	"9093e40fdf10e84d": "Financement total",
	"95345e276ffbb748": "Faire un don",
	"97a967ba9b4d7cb8": "Un soutien peut toujours voir ce qu’il a soutenu.",
	"98cfe2504cb86544": "$1 a rouvert cette initiative.",
	"9ce636b0c03051a9": "Les initiatives doivent avoir un marchand payable.",
	"9db0a701c37272b1": "Peut créer des initiatives",
	"9f727e1ef98f99a2": "Financer $1 $2",
	"a70277039afa65b3": "$1 a changé le marchand recevant les fonds pour cette initiative de $2 en $3.",
	"acde87bcfcfd2228": "$1 a défini la description de l’initiative.",
	"ad76e9a3e45067d3": "Configurer les formulaires de création et de modification de financement.",
	"ae26786e09d6aff0": "$1 a mis à jour les risques / défis de l’initiative.",
	"b8dce42ef8a134dd": "Rouvrir l’initiative ?",
	"be5b311eecb6deec": "Modifier l’initiative",
	"c11c3a01d75d93e9": "Fermer l’initiative ?",
	"c16142fef7a95177": "NOTE : vous ne contrôlez aucun des comptes d’un marchand qui peut recevoir des paiements pour cette initiative. Quand vous créez une initiative, vous devez spécifier un compte de marchant vers lequel les financements seront payés. Créez un compte de marchand dans l’application Phortune avant de créer une initiative de financement.",
	"c341b4303d2f0328": "Marchand gérant l’initiative.",
	"c71288172a3d3bde": "Tous les soutiens",
	"ca223b3429bcfeea": "$1 a de nouveau financé $2 à $3.",
	"cab1e2a32e72c57e": "Initiative fermée",
	"cab3e02528db28ee": "$1 a renommé cette initiative de $2 à $3.",
	"cb124c8ca107f157": "Voulez-vous réellement fermer cette initiative ? Les utilisateurs ne pourront plus la soutenir.",
	"cbe9285536836c4f": "Marchand $1 $2",
	"ce7cb6c7dad9da16": "DÉTAIL DE L’INITIATIVE",
	"d04483248ba0fb22": "(Marchand restreint)",
	"d23d5b2a45a044fc": "Soutenir l’initiative",
	"d4dfe251226cc952": "$1 a défini les risques / défis de l’initiative.",
	"d578e6cf37636781": "Vous devez spécifier un compte de marchand que vous contrôlez comme destinataire des financements pour cette initiative.",
	"ddcc03d2ea0658aa": "Le détenteur d’une initiative peut toujours la visualiser et la modifier.",
	"de0deb2e9931ab7a": "Soutien",
	"de63df208512aa9f": "Changements d’état d’une initiative.",
	"e1271e18f45468d9": "Visualiser les soutiens",
	"f032a5a005ba2bf4": "Configurer les formulaires de financement",
	"f56a80607051a273": "Retourner à l’initiative",
	"fe1af7cc3557a7e2": "Quelqu’un soutient une initiative."
}
