{
	"@metadata": {
		"authors": [
			"Kly"
		]
	},
	"046419b845c2560f": "使用標準色彩",
	"04cb07ada8365ae6": "不存在名稱為「$1」的資源來源！",
	"0815b2ca68359582": "無法呈現資源「$1」，此含有未知類型「$2」。",
	"0a4a18b90fc1e8c9": "正在寫入對應「$1」。",
	"0ef5ab1cc4ef90ef": "使用高對比色彩",
	"0f1ed7dfb63fc1e2": "暗黑模式（實驗功能）",
	"163ba1a9c26c97b1": "使用更大的字體大小",
	"1ef1f25b6148dbd2": "找到$1二進位資源。",
	"21cb4dca00942a97": "符號為「$1」的資源不存在於來源「$2」裡！",
	"2371af702826eab1": "Celerity",
	"2e6ee0d3a1034bf1": "用於「$1」的封包規格含有「$2」，但符號不再由任何資源$3。",
	"317174c8d84f6a62": "嘗試解決未知的資源「$1」。",
	"41fa90d128ffe8e0": "重新建置「$1」語法 CSS。",
	"4e71600bec1f4ac1": "CSS 檔案「$1」有未知的變數「$2」。",
	"6131223242825fc5": "在行內手稿不允許逐字$1。",
	"66639f7d455dd71f": "二進位",
	"7a75961209a5cf4d": "使用紅/綠（綠色盲）色彩",
	"8369c2f9ebcad3bd": "資源「$1」必須$2在至少一個 Celerity 目標。",
	"9adac865895dd02e": "在資源圖表偵測到的循環：$1",
	"a396d463559a8f47": "重新建置語法凸顯 CSS。",
	"a5dcf9b3422f14a3": "資源來源定義出兩個同名的資源「$1」。其中一個定義在「$2」對應，另一個在「$3」對應。任一資源皆要為獨一的名稱。",
	"b1191c15b7b23ea8": "來源「$1」不可有標頭 doc 註解。相關性資料編碼在 docblock 標頭。",
	"b8dcb7fb1787a65d": "用於「$1」的封包規格含有多種類型資源（$2、$3）。任一封包應僅能包含一個資源類型。",
	"bf64f63e87e16ac3": "重新建置 $1 個資源來源。",
	"ca95d79472b5600e": "找到$1文字資源。",
	"cd9aad37e951dff2": "預期於「$2」的檔案「$1」為在「$3」結尾的 Sprite 來源。",
	"cf9d8c2551d59a7f": "僅能提供靜態資源。",
	"d3909c664b071e68": "正在重新建置資源來源「$1」（$2）…",
	"d83f92dffe9f937b": "資源名稱「$1」無效，這只能包含小寫拉丁字母與數字。",
	"e67706bfcfb95cf8": "鎖定詮釋資料後嘗試添加更多詮釋資料。",
	"f57fc09b17b11893": "重新建置靜態資源對應。",
	"fe5245cd89f00746": "找到$1封包。"
}
