{
	"@metadata": {
		"authors": [
			"Kly"
		]
	},
	"02c2a0c48898b578": "建立憑證",
	"05e5d7263e6c8f40": "憑證已鎖定",
	"0acba555f26df56a": "$1鎖定了此憑證。",
	"112c57749adadcbb": "（沒有憑證）",
	"1487b403d1d02b2e": "憑證的作者能採用此操作。",
	"1879e575d007bdc3": "有效憑證",
	"1aa3aa13c00959e6": "僅顯示已銷毀憑證",
	"1b11f7bc47179a30": "防止 Conduit 存取？",
	"1bfe4ea6d6d1fff9": "新建立憑證的預設編輯方針。",
	"20962c659a2b1ca7": "憑證密鑰（$1）",
	"2319fd534ec767a5": "憑證類型",
	"24a378c8346c4111": "憑證已鎖定",
	"28ce1c6c2e9696c7": "$1銷毀了此憑證的密鑰。",
	"2c9b5d195c3babae": "$1禁止了允許 Conduit API 存取此憑證。",
	"31b45e3668174100": "$1附上了此憑證的新密鑰。",
	"36387e3ab97ca283": "所有憑證",
	"36d4c0890232043e": "永久鎖定：",
	"3798bbeab985d8f5": "憑證已鎖定",
	"3a04a90c98cbde56": "$1更新了此憑證的密鑰。",
	"3c0df61350606aa5": "在磁碟的路徑",
	"3c53366feadb8bd6": "$1建立了此憑證。",
	"3eea8bd17ac57450": "憑證無法顯示出，因為已被鎖定。",
	"438d6727af5473cd": "此憑證沒有相關的密鑰。",
	"4765182ba8d6c3ae": "（不存在憑證）",
	"47c4a89b7d09a7ee": "編輯憑證",
	"4ba458f6b5832016": "$1已鎖定憑證$2。",
	"4f563c495a6d2930": "鎖定憑證",
	"4f7bde5cf2b45cfc": "此憑證的蜜鑰為空。",
	"5008e0310f3e1e2d": "確定銷毀憑證？",
	"5377563106b88b55": "由$1在 $2 建立。",
	"569a43055121cd7e": "憑證有無法建立的類型「$1」！",
	"60eaacf0da8848c4": "SSH 私鑰（已產生）",
	"62efd0667e2a7137": "登入/使用者名稱",
	"65e0828d38a18232": "允許 Conduit 存取？",
	"6dbbabf9d5518138": "憑證「$1」為未知類型「$2」！",
	"70769ca89cd63ef3": "顯示密鑰",
	"782770bb2d9eda24": "顯示公鑰",
	"78318ed3e6ca4f20": "錯誤",
	"7d6cbe92094c0814": "僅顯示有效憑證",
	"7fd0257c136bc2e1": "此憑證已被鎖定。",
	"820dfebf41af18d9": "使用者名稱不可超過 $1 個字元。",
	"872fc079b28438ff": "新憑證",
	"8880740dc72fb636": "建立憑證",
	"89950c9c18f1aef5": "Passphrase",
	"8d644d8678e18a64": "查詢憑證。",
	"9493cfd062592ea1": "SSH 私鑰檔案",
	"964b7465a72c2d24": "憑證必須要有名稱。",
	"96e379c53b07c20c": "憑證沒有公鑰！",
	"981625e3c014d5ed": "您必須挑選憑證類型。",
	"9abf643a4ed8ee74": "Passphrase 憑證",
	"9de1796f7fb25576": "$1更新了此憑證的描述。",
	"a08d3098e318d3ff": "公鑰（$1）",
	"a1e82f03b2c9f0b5": "載入憑證「$1」失敗！",
	"a4b909283fc4e84e": "憑證作者",
	"a9d587624e3f59ef": "憑證作者",
	"abc513d7d914409d": "憑證「$1」應要提供「$2」，但卻提供了「$3」！",
	"accff681ad83e4bc": "允許 Conduit 存取",
	"ade5ddaf2557ee93": "私鑰",
	"afdc739fd465011d": "新建立憑證的預設檢視方針。",
	"afe958e756e179e8": "添加新憑證",
	"b31794cd1313133f": "憑證存儲",
	"b4adbef0970121a1": "憑證有無效類型「$1」！",
	"b8bae001a09e3fad": "$1更新了$2的密鑰。",
	"bacf6a9e6e1a29e0": "與此憑證關聯的密鑰將會以純文字顯示在您的螢幕上。",
	"bad92a18e8ce86a2": "$1允許了 Conduit API 存取憑證$2。",
	"c9037df0e6a26517": "$1允許了 Conduit API 存取此憑證。",
	"cb0edb6aac4b0ad1": "新憑證：$1",
	"cb57cee51cc4a9ec": "$1（受限制憑證）",
	"cedc4f9f00c97341": "Passphrase 憑證",
	"dbd5cfc8dd42af82": "憑證為必要！",
	"e0002efe11c34772": "此憑證必須要有使用者名稱。",
	"e3071b04185d6e6f": "與此憑證關聯的密鑰將會以純文字顯示在您的螢幕上。在繼續之前請將您的手臂環繞在螢幕四周，來形成一個人體防護罩來防止偷窺。請確實保護好公司機密！",
	"e4e025d8cee1748f": "編輯憑證：$1",
	"e555cac77d7d3f95": "銷毀憑證",
	"e7428d0baf791e2f": "SSH 私鑰",
	"e7f3b4822962134d": "無效憑證（「$1」）",
	"e9f79e62ec81f930": "查無憑證。",
	"ebe7c633f2f252f2": "$1銷毀了憑證$2的密鑰。",
	"ec1f0bd8cea1b9c8": "防止 Conduit 存取",
	"ecbc16ea01104ef2": "永久鎖定",
	"ed77bd2627b62710": "$1更新了此憑證$2的描述。",
	"f0aab7cbfa6fb809": "更改到憑證描述",
	"f87d2b297a38cc3f": "已永久鎖定",
	"fa23b7a3f9d3f2c1": "登入：$1",
	"fed54b2f7315993a": "$1將此憑證從$2改名成$3。",
	"ffd352e7ebd8982e": "確定顯示密鑰？"
}
